potatoscript/potatoPostgreSQL.py
potatoscript/test.py
python/potatoPostgreSQL.py
python/pyPostgreSQL.py
python/xMySQL.py
python/xPostgreSQL.py
xMySQL-1.1.0.dist-info/METADATA
xMySQL-1.1.0.dist-info/WHEEL
xMySQL-1.1.0.dist-info/top_level.txt
xMySQL-1.1.0.dist-info/RECORD
