Metadata-Version: 2.1
Name: xMySQL
Version: 1.1.0
Summary: A simple library for connecting to MySQL
Author: ks lim
Author-email: kianseng.lim@sony.com
